{"50348": [{"id": 1546719, "name": "Мастер-класс «Бенефис»", "age": 6, "description": "<p>Детский театральный мастер-класс – экскурсия в мир театра. Занятия актерским мастерством развивают ребенка с разных сторон. Они пригодятся и в обычной жизни, и в общении со сверстниками, укрепят уверенность в себе, помогут учиться в школе. Актерское мастерство раскрепощает, освобождает от физических и речевых зажимов, избавляет от страхов перед выступлениями и незнакомыми людьми. </p> <p>Мастер-класс включает в себя следующие разделы:</p> <ol><li>«Импровизация».</li><li>«Проблемы речи, правильное проговаривание слов для энергетического, чувственного влияния на зрителя».</li><li>«Умение удерживать внимание зала».</li><li>«Внутренний монолог и его использование».</li></ol>", "shortDescription": "Актеры народного театра и режиссер будут обучать детей азам театрального искусства.", "min_price": 300, "max_price": 300, "link": "https://vmuzey.com/event/benefis", "status": "accepted", "updateDate": 1640323670902, "start": 1641283200000, "end": 1641290400000, "createDate": 1639995912503, "inAccepted": true, "acceptDate": 1640323670955, "image": {"author": "Шарифуллин И.К.", "name": "ba848d645772e0c0bd52b386b6a17c76.jpeg", "realName": "IMG_20190315_175335.jpg", "source": "Из архива СДК"}, "photo": "https://pro.culture.ru/uploads/ba848d645772e0c0bd52b386b6a17c76.jpeg", "gallery": ["https://pro.culture.ru/uploads/1bc7d2f0a280b62cee57cf5c9288d4c5.jpeg", "https://pro.culture.ru/uploads/0175b836839a8848826ebeac7a9d8b38.jpeg", "https://pro.culture.ru/uploads/6bbd76cb57d4aea68e73370a20dca8ec.jpeg"], "category": {"name": "Обучение", "sysName": "obuchenie"}, "time": {"start": "2022-01-04 08:00:00", "end": "2022-01-04 10:00:00"}}, {"id": 1485111, "name": "Спектакль «Гололед»", "age": 6, "description": "<p>Пьеса «Гололед» писателя Зульфата Хакима в постановке и инсценировке народного театрального коллектива «Золотая маска».</p><p>Действие происходит в современности. Главная героиня Азиза теряет своего возлюбленного в автомобильной катастрофе. По случайности, свидетелем аварии оказывается молодой парень Вадим. Все вокруг обвиняют себя в произошедшем. На фоне произошедшей трагедии Азиза сходит с ума.</p><p>Перед актерами стоит важная задача: донести ценность каждого мгновения жизни, уметь прощать и отпускать обиды.<br /></p>", "shortDescription": "Постановка на татарском языке в рамках районного фестиваля «Битлек».", "min_price": 150, "link": "https://vmuzey.com/event/spektal-gololyod", "status": "accepted", "updateDate": 1638521321654, "start": 1639836000000, "end": 1639843200000, "createDate": 1637916443374, "inAccepted": true, "acceptDate": 1638521321735, "image": {"author": "Шарифуллин И.К.", "name": "a86b92732548f19bafb03c4ac0ad217d.jpeg", "realName": "2.jpeg", "source": "Архив клуба \"Тлянче-Тамакский СДК\""}, "photo": "https://pro.culture.ru/uploads/a86b92732548f19bafb03c4ac0ad217d.jpeg", "gallery": [], "category": {"name": "Спектакли", "sysName": "spektakli"}, "time": {"start": "2021-12-18 14:00:00", "end": "2021-12-18 16:00:00"}}]}