{"32134": [{"id": 1375308, "name": "Выставка «Бабы. Барышни. Девчата. Сказочная повседневность Евгения Родионова»", "age": 0, "description": "<p><span>В Музее наивного искусства откроется выставка «Бабы, барышни, девчата. Сказочная повседневность Евгения Родионова». <span>Направление, в котором работает талантливый вологодский художник, он сам для себя определяет как «родионовская роспись или родионовская живопись». Это своеобразное сочетание русской народной картинки, средневековой миниатюры, комикса, плаката, а также детских воспоминаний и увлечений.</span></span></p> <p><span>Истоки творчества Евгения Родионова обнаруживаются в русском лубке, в его поучительных и ироничных сюжетах. На выставке будет представлено более 80 работ, рассказывающих истории из реальной или сказочной женской жизни. Именно милым женским образам <span>в разноцветных платочках и кокошниках</span> посвящена эта <span>серия, над которой автор работал на протяжении почти трех лет. В зависимости от возраста, характера и настроения своих героинь он называет их то бабами (естественно, любя), то учтиво – барышнями, то по-свойски – девчатами. Причем персонажи его картин могут быть неплохо знакомы с Мэрилин Монро или запросто общаться с Атлантом, Амурами и Ломоносовым.</span></span></p>", "shortDescription": "Сочетание русской народной картинки, средневековой миниатюры, комикса, плаката, воспоминаний.", "min_price": 50, "max_price": 150, "link": "https://widget.afisha.yandex.ru/w/events/247151?clientKey=5fec60f8-7c1f-427e-8784-e34b931bce09&regionId=54", "status": "accepted", "updateDate": 1634301591508, "start": 1634796000000, "end": 1642338000000, "createDate": 1633599349970, "inAccepted": true, "acceptDate": 1634301591529, "image": {"author": "Екатеринбургский музей изобразительных искусств", "name": "3c41fa9dc73a897c02b3c9b926d2ed8a.jpeg", "realName": "0020_2018_0069_Пу Пу Пиду.jpg", "source": "Екатеринбургский музей изобразительных искусств"}, "photo": "https://pro.culture.ru/uploads/3c41fa9dc73a897c02b3c9b926d2ed8a.jpeg", "gallery": ["https://pro.culture.ru/uploads/286e729be5889f2bc0ce7cf7dd187855.jpeg", "https://pro.culture.ru/uploads/bfe83d955614d1ca89c29292612d9a9a.jpeg"], "category": {"name": "Выставки", "sysName": "vystavki"}, "time": {"start": "2021-10-21 06:00:00", "end": "2022-01-16 13:00:00"}}, {"id": 1265044, "name": "Выставка «Дорога с войны»", "age": 12, "description": "<p>На выставке представлены более 60 графических и живописных работ шести авторов – художников-любителей и тех «афганцев», что выбрали путь профессионального художника.</p> <p>По словам организаторов, основная идея выставки – показать, как художественное творчество помогает ветеранам Афганской войны вернуться к мирной жизни и избавиться от психологических травм.</p> <p></p> <p>Посетители увидят полотна, на которых изображены советские военнослужащие в Афганистане во время боевых действий, местные жители и пейзажи этой страны, а также работы, на которых запечатлена послевоенная, мирная жизнь. В качестве иллюстраций быта советских солдат в Афганистане на выставке экспонируются артефакты – обмундирование, деньги и чеки, элементы боеприпасов.</p> <p>В пространстве выставки будут проходить регулярные экскурсии, занятия с детьми, а также творческие встречи с «афганцами». </p> <p>Выставка пройдет в рамках проекта «Афганцы в городе», реализуемого Свердловской областной организацией имени Героя Советского Союза Ю.В. Исламова Общероссийской общественной организации «Российский Союз ветеранов Афганистана» при поддержке Фонда президентских грантов.</p>", "shortDescription": "Выставка покажет, как творчество помогает участникам событий преодолеть пережитое на войне.", "min_price": 50, "max_price": 150, "link": "https://widget.afisha.yandex.ru/w/events/239430?clientKey=5fec60f8-7c1f-427e-8784-e34b931bce09&regionId=54", "needCheck": true, "status": "accepted", "updateDate": 1631085533678, "start": 1630476000000, "end": 1633874400000, "createDate": 1628600426197, "inAccepted": true, "acceptDate": 1631085536202, "image": {"author": "Екатеринбургский музей изобразительных искусств", "name": "8e4dc389d1fd6cbf0efebe18ebe70dfd.jpeg", "realName": "Кулев П. Ворота в ущелье Ширали-Комар 40х60.jpg", "source": "Екатеринбургский музей изобразительных искусств"}, "photo": "https://pro.culture.ru/uploads/8e4dc389d1fd6cbf0efebe18ebe70dfd.jpeg", "gallery": ["https://pro.culture.ru/uploads/608ccb367ae477e2f8a6386f2ef69ead.jpeg", "https://pro.culture.ru/uploads/afc763ba3c81ba3b0aea2524d72918a3.jpeg", "https://pro.culture.ru/uploads/bfaac8e7b83efc71f3d60364ee2ddb3e.jpeg"], "category": {"name": "Выставки", "sysName": "vystavki"}, "time": {"start": "2021-09-01 06:00:00", "end": "2021-10-10 14:00:00"}}, {"id": 1245507, "name": "Выставка работ Альберта Коровкина", "age": 6, "description": "<p>Постоянная экспозиция известного уральского художника Альберта Николаевича Коровкина (1935-2021). Этот автор является гордостью музея наивного искусства, а его работы – подлинными жемчужинами собрания наивного искусства. Картины и скульптуры из стекла Коровкина хранятся во многих собраниях Екатеринбурга, Москвы, Суздаля, а его имя вошло во «Всемирную энциклопедию наивного искусства». Работы мастера с конца 1960-х участвовали во всесоюзных и международных выставках в Свердловске, Москве, ГДР, Франции, Бельгии. Альберт Николаевич работал в разных видах искусства – живописи по дереву, напоминающей лубок и иконопись, скульптуре из мрамора, дерева и металла, различных графических техниках, в том числе и изобретенных самим автором. И все же наиболее впечатляющим является его фантастический зверинец – произведения, выполненные в стеклодувной технике. Более двадцати лет Коровкин проработал в мастерских Уральского научного центра, где занимался изготовлением научных приборов из молибденового стекла. Особенно поражает тот факт, что его скульптуры выполнены не из мягкого художественного, а из тугоплавкого аппаратного стекла, не предназначенного для творческих произведений.</p> <p>Всего в «Зале Коровкина» выставлено 40 произведений живописи, 10 графических работ и около 30 скульптур из стекла.</p>", "shortDescription": "Гости увидят произведения известного наивного художника.", "min_price": 50, "max_price": 150, "link": "https://widget.afisha.yandex.ru/w/sessions/MTU5MDN8MjIwMDk1fDIyODM2NXwxNjMyOTcwODAwMDAw?clientKey=5fec60f8-7c1f-427e-8784-e34b931bce09", "status": "accepted", "updateDate": 1630865097870, "start": 1630476000000, "end": 1662040800000, "createDate": 1627646855983, "inAccepted": true, "acceptDate": 1630865102443, "image": {"author": "Екатеринбургский музей изобразительных искусств", "name": "9d6be19953c05a785a0aab7382ecd6ce.jpeg", "realName": "gmTZK2aq1do.jpg", "source": "Екатеринбургский музей изобразительных искусств"}, "photo": "https://pro.culture.ru/uploads/9d6be19953c05a785a0aab7382ecd6ce.jpeg", "gallery": ["https://pro.culture.ru/uploads/2152ff6c346d0129a2698aa301fb7d6a.jpeg", "https://pro.culture.ru/uploads/431bda4edfd03208b1f8583e67006b6d.jpeg", "https://pro.culture.ru/uploads/7aed3b40337c4f54bc607d6685d1f34c.jpeg", "https://pro.culture.ru/uploads/b8acdfea0d41f390fadf8a3563342523.jpeg", "https://pro.culture.ru/uploads/06aa0f09dcc1078a668be514b7be1201.jpeg", "https://pro.culture.ru/uploads/2512d3b84c77f1cedc26a58333a02002.jpeg"], "category": {"name": "Выставки", "sysName": "vystavki"}, "time": {"start": "2021-09-01 06:00:00", "end": "2022-09-01 14:00:00"}}]}