{"843": [{"id": 1467779, "name": "Квест «Найди экспонат»", "age": 16, "description": "<p>Участникам мероприятия предстоит отправиться в экспедицию по залам краеведческого музея и научиться извлекать информацию из вещественных источников, узнавать о выдающихся людях, их занятиях, быте, достопримечательностях, событиях, связанных с историей Волоконовского района. </p><p>С помощью маршрутных листов с непростыми и интересными заданиями ребята окунутся в таинственный мир прошлого. Листы содержат занимательные вопросы, ответы на которые можно найти, лишь внимательно изучив экспозицию музея, ребусы, головоломки. Подсказкой станут музейные экспонаты и подписи к ним. </p>", "shortDescription": "Путешествие по страницам истории родного края.", "min_price": 15, "max_price": 15, "link": "https://bel.cultreg.ru/events/107962/kvest-naidi-eksponat", "status": "accepted", "updateDate": 1637754800778, "start": 1639047600000, "end": 1640865600000, "createDate": 1637308515762, "inAccepted": true, "acceptDate": 1637754804503, "image": {"author": "Газета КУЛЬТУРА", "name": "32abcaf31b1c462d3a6c4cadde2ae37f.jpeg", "realName": "Quest_Kult_03_02.jpg", "source": "https://portal-kultura.ru/articles/best/151553-idushchie-na-kvest/"}, "photo": "https://pro.culture.ru/uploads/32abcaf31b1c462d3a6c4cadde2ae37f.jpeg", "gallery": [], "category": {"name": "Встречи", "sysName": "vstrechi"}, "time": {"start": "2021-12-09 11:00:00", "end": "2021-12-30 12:00:00"}}, {"id": 1463111, "name": "Музейное занятие «Искусство, ставшее судьбой»", "age": 12, "description": "<p>Мероприятие будет проходить в постоянной экспозиции художественного зала музея. Посетителей ждет знакомство с жизнью и произведениями из коллекции заслуженного художника России В. М. Лузанова. </p><p>Участники мероприятия познакомятся с жанрами живописи: портретом, пейзажем, натюрмортом. Также гости окунутся в яркую и незабываемую атмосферу мира искусства. Ребята узнают, из чего состоит профессия художника, в чем ее смысл и что такое жизнь в мире красок. А также дети, как настоящие художники, смогут перевоплотиться в живописцев и нарисовать свои чудеса.</p>", "shortDescription": "Знакомство с творчеством талантливого земляка.", "min_price": 15, "max_price": 15, "link": "https://bel.cultreg.ru/events/107963/muzeinaya-masterskaya-iskusstvo-stavshee-sudboiка", "status": "accepted", "updateDate": 1637754707785, "start": 1638871200000, "end": 1639738800000, "createDate": 1637157671901, "inAccepted": true, "acceptDate": 1637754710688, "image": {"author": "Волоконовский РКМ", "name": "a7a496ebb6a6a35337b71a30c291c37d.jpeg", "realName": "DDd8L2qEE_g.jpg", "source": "Волоконовский РКМ"}, "photo": "https://pro.culture.ru/uploads/a7a496ebb6a6a35337b71a30c291c37d.jpeg", "gallery": [], "category": {"name": "Обучение", "sysName": "obuchenie"}, "time": {"start": "2021-12-07 10:00:00", "end": "2021-12-17 11:00:00"}}]}