{"56668": [{"id": 1490211, "name": "Рок-опера «Юнона и Авось»", "age": 12, "description": "<p>Авторы постановки – выдающийся русский композитор Алексей Рыбников и поэт Андрей Вознесенский. Постановку в авторской версии осуществил Государственный театр под руководством народного артиста РФ, лауреата Государственной премии РФ, композитора Алексея Львовича Рыбникова.</p><p> Главный акцент сделан на музыкальной составляющей. Вокальные номера поставлены прославленной певицей, заслуженной артисткой РФ Жанной Рождественской – первой исполнительницей главных партий в рок-операх Алексея Рыбникова и многих знаменитых шлягерах советского кино («Позвони мне, позвони», «Песня гадалки»). </p><p>Великолепные хореографические номера в постановке Жанны Шмаковой (хореограф-постановщик мюзиклов «Буратино», «Продюсеры», «Иствикские ведьмы», рок-оперы «Хоакин Мурьета») делают постановку ярким и незабываемым зрелищем. </p><p>Главный режиссер – Александр Рыхлов, один из лучших московских режиссеров музыкального театра, известный своими работами в театре, телевизионными и концертными программами. <br /></p>", "shortDescription": "Самая известная программа на российской сцене.", "min_price": 1000, "max_price": 4000, "link": "https://kaliningrad.ticketland.ru/koncertnye-zaly/yantar-kholl/yunona-i-avos-kaliningrad/", "needCheck": true, "status": "accepted", "updateDate": 1640642104536, "start": 1642946400000, "end": 1653588000000, "createDate": 1638189675326, "inAccepted": true, "acceptDate": 1639985853431, "image": {"author": "Ксения", "name": "78f6e202392290fa56a9458b9dcad26f.jpeg", "realName": "фото-(2)-640х420.jpg", "source": "ООО \"КС\""}, "photo": "https://pro.culture.ru/uploads/78f6e202392290fa56a9458b9dcad26f.jpeg", "gallery": [], "category": {"name": "Спектакли", "sysName": "spektakli"}, "time": {"start": "2022-01-23 14:00:00", "end": "2022-05-26 18:00:00"}}, {"id": 900057, "name": "Концерт «Берегите Россию»", "age": 6, "description": "<p> Уральский народный хор представит зрителю новые, а также полюбившиеся песни, танцы и музыку военных лет. Прозвучат те самые мелодии, что вселяли надежду в Победу! Также в программе – уральские танцы и народные песни, которые не переставали звучать и в самые тяжелые годы. Главный девиз концерта Уральского народного хора – «Берегите Россию всей душой». Берегите своих близких и любимых!</p><p> </p><p>В программе: </p><ul><li>вокально-хореографическая картина «Русь молодая» (музыка и слова А. Петрова); </li><li>«Мы вращаем землю» (музыка и слова В. Высоцкого); </li><li>«Баллада о солдате» (музыка В. Соловьева-Седого, слова М. Матусовского); </li><li>вокально-хореографическая картина «Журавли» (музыка Я. Френкеля, слова Р. Гамзатова); </li><li>«Скажи, скажи, когда вернешься» (романс с. Катарач Свердловской области); </li><li>«За околицей» (музыка А. Устьянцева, постановка А. Черепанова).</li></ul>", "shortDescription": "Новая программа Уральского народного хора.", "min_price": 300, "max_price": 1200, "link": "https://urfolk-art.ru/events/event/beregite-rossiju-3/?utm_source=culture&utm_medium=afisha&utm_campaign=brkosmos", "needCheck": true, "status": "accepted", "updateDate": 1635492341111, "start": 1613656800000, "end": 1638288000000, "createDate": 1611139107168, "inAccepted": true, "acceptDate": 1635492341401, "image": {"author": "Тарас Ерошин", "name": "e3f0469e68e2e9c8ad1983cc964ffcd2.jpeg", "realName": "IMG_7291.JPG", "source": "https://urfolk-art.ru/galereja/"}, "photo": "https://pro.culture.ru/uploads/e3f0469e68e2e9c8ad1983cc964ffcd2.jpeg", "gallery": [], "category": {"name": "Концерты", "sysName": "koncerty"}, "time": {"start": "2021-02-18 14:00:00", "end": "2021-11-30 16:00:00"}}]}