{"53946": [{"id": 1499844, "name": "Выставка «Фронтовая слава Забайкалья»", "age": 0, "description": "<p>Выставка-экспозиция «Фронтовая слава Забайкалья» состоит из нескольких стендов: «Равнение на Героев Отечества», «Бессмертный полк солдат Победы», «Подвигом славны забайкальцы!», «Могойтуйцы в боях за Родину», «Они не вернулись из боя», «Фронтовая слава Забайкалья». </p><p>Экспозиция размещается на выставочных стендах-раскладушках размером 135х190 см. Каждый стенд рассказывает о фронтовых заслугах и боевых подвигах земляков-могойтуйцев. Более двух тысяч могойтуйцев защищали Родину на фронтах Великой Отечественной и второй мировой войн. Среди них – два Героя Советского Союза, сотни земляков награждены боевыми орденами и медалями.<br /></p>", "shortDescription": "Экспозиция, посвященная Дню Героев Отечества.", "min_price": 400, "max_price": 500, "link": "https://vmuzey.com/event/220-letiyu-cugolskogo-dacana", "needCheck": true, "status": "accepted", "updateDate": 1640404666669, "start": 1638838800000, "end": 1640854800000, "createDate": 1638431897073, "inAccepted": true, "acceptDate": 1639719276841, "image": {"author": "Бато Жапов", "name": "519f1156bd199d7677bcd0a7d94f88bd.jpeg", "realName": "Фронтовая слава Забайкалья1.jpg", "source": "архив автора"}, "photo": "https://pro.culture.ru/uploads/519f1156bd199d7677bcd0a7d94f88bd.jpeg", "gallery": [], "category": {"name": "Выставки", "sysName": "vystavki"}, "time": {"start": "2021-12-07 01:00:00", "end": "2021-12-30 09:00:00"}}, {"id": 1498806, "name": "Выставка «Цугольский дацан – жемчужина буддизма Забайкалья»", "age": 0, "description": "<p></p><p></p><p>В июле 2021 года Цугольский дацан отметил 220 лет со дня своего создания. На стенде, посвященном его юбилею, размещено 19 фотографий форматом А4. Они рассказывают об истории и развитии Цугольского дацана, знакомят с его архитектурными особенностями. Для посетителей это интересные кадры из истории старейшего буддийского храма на территории Забайкальского края. </p><p>Гости выставки также увидят фрагменты оформления главного здания дацана – Согчен-дугана – и другие достопримечательности. На стенде помещена фотография Дамбинимы Цырендашиева – учителя и краеведа, который на протяжении всей своей жизни собирал материалы по истории Цугольского дацана, работал с архивными материалами, беседовал со старожилами. Он автор книги, которая внесла поистине неоценимый вклад в историю буддизма, в частности, в историю Цугольского дацана и о его знаменитых священнослужителей. Она написана на бурятском языке. Ее первый тираж составлял всего 300 экземпляров.</p>", "shortDescription": "Передвижная экспозиция, посвященная 220-летию старейшего монастыря.", "min_price": 400, "max_price": 500, "link": "https://vmuzey.com/event/cugolskiy-dacan-zhemchuzhina-buddizma-zabaykalya", "needCheck": true, "status": "accepted", "updateDate": 1640404853896, "start": 1638838800000, "end": 1640854800000, "createDate": 1638413291642, "inAccepted": true, "acceptDate": 1639565411088, "image": {"author": "Бато Жапов", "name": "0cfe2d0e96f4d4528cc53f50b2d8f10e.jpeg", "realName": "Презентация1.jpg", "source": "Источник автора"}, "photo": "https://pro.culture.ru/uploads/0cfe2d0e96f4d4528cc53f50b2d8f10e.jpeg", "gallery": [], "category": {"name": "Выставки", "sysName": "vystavki"}, "time": {"start": "2021-12-07 01:00:00", "end": "2021-12-30 09:00:00"}}]}