{"19111": [{"id": 1248491, "name": "Обзорная экскурсия по экспозиции «Воронежская область в годы Великой Отечественной войны»", "age": 0, "description": "<p> В ходе мероприятия гости узнают о трагических событиях в жизни области и города Воронежа в годы Великой Отечественной войны. Экскурсантам расскажут о развитии промышленности и сельского хозяйства города в начале войны, сделают акцент на помощи тыла в борьбе с немецко-фашистскими захватчиками. Экспозиция предоставит возможность посетителям детальнее познакомиться с основными событиями Воронежского сражения (28 июня 1942 – 2 февраля 1943), оккупации области, деятельностью партизан. Особое внимание уделяется этапу освобождения Воронежа, пути Воронежского фронта и окончанию Великой Отечественной войны.</p><p>Для посещения экскурсии необходимо приобрести входной билет.</p><p> </p>", "shortDescription": "Посетителя познакомятся с основными событиями войны на территории Воронежского края.", "min_price": 150, "max_price": 200, "link": "http://museum-vrn.ru/", "status": "accepted", "updateDate": 1629445282752, "start": 1630483200000, "end": 1635687000000, "createDate": 1627893021837, "inAccepted": true, "acceptDate": 1629710598523, "image": {"author": "Пичкурова М.И.", "name": "8c42a6b013ae13df29563ee2572cb01c.jpeg", "realName": "9a65aa628b1c1a98f80f7176789057ac.jpeg", "source": "Воронежский областной краеведческий музей"}, "photo": "https://pro.culture.ru/uploads/8c42a6b013ae13df29563ee2572cb01c.jpeg", "gallery": [], "category": {"name": "Встречи", "sysName": "vstrechi"}, "time": {"start": "2021-09-01 08:00:00", "end": "2021-10-31 13:30:00"}}]}