{"19678": [{"id": 1522506, "name": "Встреча «Елочные забавы»", "age": 0, "description": "<p><span>Близится Новый год – праздник, пахнущий хвоей и мандаринами. Его сложно представить себе без зеленой красавицы и елочных игрушек. </span></p><p><span>В библиотеке состоится очередная встреча с учащимися, в ходе которой ребят ждет мастер-класс по изготовлению новогодних игрушек. Библиотекарь подготовил для ребят историю о возникновении традиции делать украшения и наряжать ими новогодние елки, но самым интересным занятием будет, конечно же, изготовление елочных игрушек своими руками. Кроме того, детей ждут игры и кроссворды. </span></p>", "shortDescription": "Знакомство с новогодними традициями, занятие по изготовлению елочной игрушки, игры.", "min_price": 100, "link": "https://vmuzey.com/event/master-klass-elochnye-zabavy", "status": "accepted", "updateDate": 1640177724340, "start": 1640595600000, "end": 1640599200000, "createDate": 1639116146611, "inAccepted": true, "acceptDate": 1640177724507, "image": {"author": "Интернет", "name": "e8925369d075991048478722087ef282.jpeg", "realName": "lHsGfVBo6V8.jpg", "source": "Интернет"}, "photo": "https://pro.culture.ru/uploads/e8925369d075991048478722087ef282.jpeg", "gallery": [], "category": {"name": "Встречи", "sysName": "vstrechi"}, "time": {"start": "2021-12-27 09:00:00", "end": "2021-12-27 10:00:00"}}]}