{"24886": [{"id": 1523440, "name": "Концерт Юрия Нугманова", "age": 6, "description": "<p>В концерте прозвучит испанская, русская, латиноамериканская музыка, известные мелодии из фильмов, мировые шедевры гитарной музыки. </p><p>Юрий охватывает все многообразие стилей и жанров гитарной музыки от шедевров, с которых начиналась гитарная классика, до современных авторов и авангарда.</p> <p>В репертуаре музыканта есть классические концерты А. Вивальди, Л. Боккерини, А. Фалькенхагена, Х.Родриго, М. Кастельнуово-Тедеско, Э. Кордеро, оригинальные сочинения для гитары и переложения, созданные композиторами разных стран мира в течение нескольких столетий: музыка Баха и Моцарта, Паганини и Чайковского, Альбениса и Пьяццоллы, Дунаевского, Орехова, Кошкина, Иванова-Крамского, Тарреги, Альбениса, Кориа и других известных композиторов. Исполняет Ю. Нугманов романсы и народные песни (не только русские, но и латиноамериканские), джазовые мелодии.<br /></p> <p></p>", "shortDescription": "Артист представит программу «Вся жизнь – гитара».", "min_price": 500, "max_price": 3000, "link": "https://nsk.kassir.ru/koncert/yuriy-nugmanov-3#973488", "status": "accepted", "updateDate": 1640340799757, "start": 1643025600000, "end": 1643032800000, "createDate": 1639128363274, "inAccepted": true, "acceptDate": 1640269359875, "image": {"author": "Юрий Нугманов", "name": "3d03e809eb2a813cd5b26e0f32bde271.jpeg", "realName": "юра.jpeg", "source": "https://vk.com/id17959793"}, "photo": "https://pro.culture.ru/uploads/3d03e809eb2a813cd5b26e0f32bde271.jpeg", "gallery": ["https://pro.culture.ru/uploads/8ba24c8dd3a302a6a3bd3facd628322a.jpeg"], "category": {"name": "Концерты", "sysName": "koncerty"}, "time": {"start": "2022-01-24 12:00:00", "end": "2022-01-24 14:00:00"}}]}